uploader_client/__init__.py
uploader_client/adapters.py
uploader_client/configurations.py
uploader_client/const.py
uploader_client/models.py
uploader_client/utils.py
uploader_client/contrib/__init__.py
uploader_client/contrib/rdm/__init__.py
uploader_client/contrib/rdm/interfaces/__init__.py
uploader_client/contrib/rdm/interfaces/cache.py
uploader_client/contrib/rdm/interfaces/configurations.py
uploader_client/contrib/rdm/interfaces/rdm.json
uploader_client/contrib/rdm/interfaces/rest.py
uploader_client/contrib/rdm/interfaces/utils.py
uploader_client/contrib/rdm/interfaces/validation.py
uploader_client/interfaces/__init__.py
uploader_client/interfaces/base.py
uploader_client/interfaces/rest.py
uploader_client/logging/__init__.py
uploader_client/logging/base.py
uploader_client/logging/db.py
uploader_client/logging/stdlib.py
uploader_client/migrations/0001_initial.py
uploader_client/migrations/__init__.py
uploader_client-0.4.0.dist-info/METADATA
uploader_client-0.4.0.dist-info/WHEEL
uploader_client-0.4.0.dist-info/dependency_links.txt
uploader_client-0.4.0.dist-info/top_level.txt
uploader_client-0.4.0.dist-info/RECORD
