Metadata-Version: 2.4
Name: uploader-client
Version: 0.4.0
Summary: Клиент для взаимодействия с Загрузчиком данных в витрину
Author: BARS Group
Author-email: education_dev@bars-open.ru
License: MIT
Classifier: Intended Audience :: Developers
Classifier: Environment :: Web Environment
Classifier: Natural Language :: Russian
Classifier: Operating System :: OS Independent
Classifier: Programming Language :: Python
Classifier: Programming Language :: Python :: 3.7
Classifier: Programming Language :: Python :: 3.8
Classifier: Programming Language :: Python :: 3.9
Classifier: Development Status :: 5 - Production/Stable
Classifier: Framework :: Django :: 2.2
Classifier: Framework :: Django :: 3.0
Classifier: Framework :: Django :: 3.1
Classifier: Framework :: Django :: 3.2
Classifier: Framework :: Django :: 4.0
Classifier: Framework :: Django :: 4.1
Requires-Dist: httpx<=0.38.1
Requires-Dist: pydantic<=1.11
Requires-Dist: requests<=2.32
Requires-Dist: django<=5,>=2.2.28
Requires-Dist: openapi-core<=0.19,>=0.14.5
Dynamic: author
Dynamic: author-email
Dynamic: classifier
Dynamic: description
Dynamic: description-content-type
Dynamic: license
Dynamic: requires-dist
Dynamic: summary
